{"version":1,"resource":"file:///mnt/hdd/HDD%28lost%2Bfound%29/instant_chef_project/recipe_filter/app.js","entries":[{"id":"bX11.js","timestamp":1734680586539},{"id":"USgf.js","timestamp":1734680605607},{"id":"JmoC.js","timestamp":1734680648005},{"id":"7euY.js","timestamp":1734680778566},{"id":"R8lF.js","timestamp":1734681168120},{"id":"s423.js","timestamp":1734681181816},{"id":"8UOF.js","timestamp":1734681216882},{"id":"82Z3.js","timestamp":1734681256092},{"id":"bNrv.js","timestamp":1734681334990},{"id":"dLEA.js","timestamp":1734681368817},{"id":"OEzw.js","timestamp":1734681400221},{"id":"93mc.js","timestamp":1734681506600},{"id":"21FO.js","timestamp":1734681604737},{"id":"323O.js","timestamp":1734681855471},{"id":"z7eM.js","timestamp":1734688281379},{"id":"WBRr.js","timestamp":1734688292665},{"id":"onMk.js","timestamp":1734688352791},{"id":"n0VI.js","timestamp":1734689901802},{"id":"BLIq.js","timestamp":1734690262449},{"id":"6qhi.js","timestamp":1734690492753},{"id":"5dgl.js","timestamp":1734691082172},{"id":"Am5n.js","timestamp":1734691143254},{"id":"L7GI.js","timestamp":1734691208509},{"id":"BmC5.js","timestamp":1734700176223},{"id":"6l4s.js","timestamp":1734700793429},{"id":"hpfL.js","timestamp":1734705243225},{"id":"MJ2C.js","timestamp":1734705276875},{"id":"Oyok.js","timestamp":1734705319963},{"id":"6QIa.js","timestamp":1734705347722},{"id":"9nw2.js","timestamp":1734705378897}]}